my_library/function.py
statistool_0001-0.0.1.dist-info/LICENSE
statistool_0001-0.0.1.dist-info/METADATA
statistool_0001-0.0.1.dist-info/WHEEL
statistool_0001-0.0.1.dist-info/top_level.txt
statistool_0001-0.0.1.dist-info/RECORD
