Metadata-Version: 2.1
Name: statistool-0001
Version: 0.0.1
Summary: useful tool
Home-page: https://github.com/VERUS2621/statis0001
Download-URL: https://github.com/VERUS2621/statis0001
Author: kangmin
Classifier: Programming Language :: Python :: 3
License-File: LICENSE
